fileflamingo/BaseFile.py
fileflamingo/EncryptionFile.py
fileflamingo/Encryptor.py
fileflamingo/Exceptions.py
fileflamingo/RSAFile.py
fileflamingo/TextFile.py
fileflamingo/__init__.py
fileflamingo-0.0.7.dist-info/LICENSE
fileflamingo-0.0.7.dist-info/METADATA
fileflamingo-0.0.7.dist-info/WHEEL
fileflamingo-0.0.7.dist-info/top_level.txt
fileflamingo-0.0.7.dist-info/RECORD
