Metadata-Version: 2.1
Name: fileflamingo
Version: 0.0.7
Summary: A suite of Python base classes that simplify interactions with files.
Home-page: https://github.com/jgrugru/file-flamingo
Author: Jeff Gruenbaum
Author-email: jeff.gruenbaum@gmail.com
License: MIT
Keywords: file,file abstraction,file functions,fileclass,class file,mixin
Platform: UNKNOWN
Classifier: License :: OSI Approved :: MIT License
Classifier: Programming Language :: Python :: 3
Classifier: Programming Language :: Python :: 3.7
Requires-Dist: pycryptodome (==3.10.1)
